{
  "kind": "collectionType",
  "collectionName": "impact_stats",
  "info": {
    "singularName": "impact-stat",
    "pluralName": "impact-stats",
    "displayName": "Impact Stat"
  },
  "options": {
    "draftAndPublish": true
  },
  "pluginOptions": {},
  "attributes": {
    "number": {
      "type": "integer",
      "required": true
    },
    "label": {
      "type": "string",
      "required": true
    },
    "icon": {
      "type": "string"
    },
    "description": {
      "type": "text"
    },
    "order": {
      "type": "integer",
      "default": 0
    }
  }
}
